YouGlance/__init__.py
YouGlance/spy.py
YouGlance-0.0.9.dist-info/LICENSE
YouGlance-0.0.9.dist-info/METADATA
YouGlance-0.0.9.dist-info/WHEEL
YouGlance-0.0.9.dist-info/top_level.txt
YouGlance-0.0.9.dist-info/RECORD
